mmar_utils/__init__.py
mmar_utils/decorators_limit_concurrency.py
mmar_utils/decorators_on_error_log_and_none.py
mmar_utils/decorators_retry.py
mmar_utils/decorators_trace_with.py
mmar_utils/io_asyncio.py
mmar_utils/mmar_types.py
mmar_utils/parallel_map.py
mmar_utils/py.typed
mmar_utils/utils.py
mmar_utils/utils_collections.py
mmar_utils/utils_inspect.py
mmar_utils/utils_texts.py
mmar_utils/utils_texts_postprocessing.py
mmar_utils/validators.py
mmar_utils-1.1.17.dist-info/licenses/LICENSE
mmar_utils-1.1.17.dist-info/WHEEL
mmar_utils-1.1.17.dist-info/METADATA
mmar_utils-1.1.17.dist-info/RECORD
