Metadata-Version: 2.4
Name: mmar-utils
Version: 1.1.17
Summary: Utilities for multi-modal architectures team
Keywords: 
Author: Eugene Tagin
Author-email: Eugene Tagin <tagin@airi.net>
License-Expression: MIT
License-File: LICENSE
Classifier: Development Status :: 4 - Beta
Classifier: Intended Audience :: Developers
Classifier: Programming Language :: Python
Classifier: Programming Language :: Python :: 3
Classifier: Programming Language :: Python :: 3 :: Only
Classifier: Programming Language :: Python :: 3.12
Classifier: Programming Language :: Python :: 3.13
Classifier: Programming Language :: Python :: 3.14
Classifier: Topic :: Documentation
Classifier: Topic :: Software Development
Classifier: Topic :: Utilities
Classifier: Typing :: Typed
Requires-Dist: pydantic~=2.12.5
Requires-Dist: tqdm~=4.67.0
Requires-Dist: types-tqdm~=4.67.0
Requires-Python: >=3.11
